clidb/__init__.py
clidb/cli.py
clidb/database.py
clidb/events.py
clidb/views.py
clidb/workspace.code-workspace
clidb-0.2.3.dist-info/entry_points.txt
clidb-0.2.3.dist-info/LICENSE
clidb-0.2.3.dist-info/WHEEL
clidb-0.2.3.dist-info/METADATA
clidb-0.2.3.dist-info/RECORD
