Metadata-Version: 2.1
Name: clidb
Version: 0.2.3
Summary: CLI based SQL client for local data
Home-page: https://github.com/dannyboland/clidb
License: MIT
Author: Danny Boland
Author-email: danny@boland.dev
Requires-Python: >=3.8,<4.0
Classifier: Development Status :: 3 - Alpha
Classifier: Environment :: Console
Classifier: Intended Audience :: Developers
Classifier: Intended Audience :: Information Technology
Classifier: Intended Audience :: Science/Research
Classifier: License :: OSI Approved :: MIT License
Classifier: Natural Language :: English
Classifier: Programming Language :: Python :: 3
Classifier: Programming Language :: Python :: 3.10
Classifier: Programming Language :: Python :: 3.8
Classifier: Programming Language :: Python :: 3.9
Classifier: Topic :: Database
Classifier: Topic :: Utilities
Classifier: Typing :: Typed
Provides-Extra: extras
Requires-Dist: boto3 (>=1.20,<2.0); extra == "extras"
Requires-Dist: duckdb (>=0.3.2,<0.4.0)
Requires-Dist: fsspec (>=2022.2.0,<2023.0.0); extra == "extras"
Requires-Dist: openpyxl (>=3.0.9,<4.0.0); extra == "extras"
Requires-Dist: pandas (>=1.3,<2.0); extra == "extras"
Requires-Dist: pyarrow (>=7.0.0,<8.0.0); extra == "extras"
Requires-Dist: s3fs (>=2022.2.0,<2023.0.0); extra == "extras"
Requires-Dist: textual (==0.1.18)
Requires-Dist: textual-inputs (>=0.2.0,<0.3.0)
Requires-Dist: xlrd (>=2.0.1,<3.0.0); extra == "extras"
